yeonji/__init__.py
yeonji/__pkginfo__.py
yeonji/borgsize.py
yeonji/flacco.py
yeonji/fsclean.py
yeonji/me2dlc.py
yeonji/mkvthumb.py
yeonji/pypi.py
yeonji/ytd.py
yeonji/ytdlj.py
yeonji/yttag.py
yeonji-1.0.0.dist-info/entry_points.txt
yeonji-1.0.0.dist-info/LICENSE
yeonji-1.0.0.dist-info/WHEEL
yeonji-1.0.0.dist-info/METADATA
yeonji-1.0.0.dist-info/RECORD
