Metadata-Version: 2.1
Name: yeonji
Version: 1.0.0
Summary: Collection of command line tools
Keywords: scripts,commandline
Author-email: Johannes Krattenmacher <yeonji@dev.krateng.ch>
Requires-Python: >=3.6
Classifier: Programming Language :: Python :: 3
Classifier: License :: OSI Approved :: GNU General Public License v3 (GPLv3)
Classifier: Operating System :: OS Independent
Requires-Dist: tabulate
Requires-Dist: send2trash
Requires-Dist: doreah>=1.6.11
Requires-Dist: unidecode
Requires-Dist: emoji
Requires-Dist: yt-dlp
Project-URL: documentation, https://github.com/krateng/yeonji
Project-URL: repository, https://github.com/krateng/yeonji
